shared_libraries/__init__.py
esl_babylon_library_common-0.1.0.57.dist-info/METADATA
esl_babylon_library_common-0.1.0.57.dist-info/WHEEL
esl_babylon_library_common-0.1.0.57.dist-info/RECORD
