Metadata-Version: 2.3
Name: esl-babylon-library-common
Version: 0.1.0.57
Summary: 
Author: placeholder
Author-email: placeholder@placeholder.com
Requires-Python: >=3.11,<3.12
Classifier: Programming Language :: Python :: 3
Classifier: Programming Language :: Python :: 3.11
Requires-Dist: colorama (>=0.4.6,<0.5.0)
Requires-Dist: fastapi (>=0.115.11,<0.116.0)
Requires-Dist: fpdf2 (>=2.8.2,<3.0.0)
Requires-Dist: langchain (>=0.3.19,<0.4.0)
Requires-Dist: langchain-google-genai (>=2.0.11,<3.0.0)
Requires-Dist: langchain-openai (>=0.3.7,<0.4.0)
Requires-Dist: opentelemetry-api (>=1.30.0,<2.0.0)
Requires-Dist: opentelemetry-exporter-otlp (>=1.30.0,<2.0.0)
Requires-Dist: opentelemetry-exporter-otlp-proto-grpc (>=1.30.0,<2.0.0)
Requires-Dist: opentelemetry-sdk (>=1.30.0,<2.0.0)
Requires-Dist: pydantic-settings (>=2.8.1,<3.0.0)
Requires-Dist: pymongo (>=4.11.2,<5.0.0)
Requires-Dist: pypdf2 (>=3.0.1,<4.0.0)
Requires-Dist: python-docx (>=1.1.2,<2.0.0)
Requires-Dist: python-dotenv (>=1.0.1,<2.0.0)
Requires-Dist: redis (>=5.2.1,<6.0.0)
Requires-Dist: reportlab (>=4.3.1,<5.0.0)
